Ionomy/__init__.py
Ionomy/bit_panda.py
Ionomy/bit_ta.py
Ionomy/bittrex.py
Ionomy/ion_panda.py
Ionomy/ionomy.py
Ionomy/utils/__init__.py
Ionomy/utils/dataframes.py
ionomy_python-0.0.7.dist-info/LICENSE
ionomy_python-0.0.7.dist-info/METADATA
ionomy_python-0.0.7.dist-info/WHEEL
ionomy_python-0.0.7.dist-info/entry_points.txt
ionomy_python-0.0.7.dist-info/top_level.txt
ionomy_python-0.0.7.dist-info/RECORD
