Metadata-Version: 2.1
Name: ionomy-python
Version: 0.0.7
Summary: UNKNOWN
Home-page: https://github.com/Distortedlogic/ionomy-python
Author: DistortedLogic/Memehub
Author-email: jermeek@gmail.com
License: LICENSE.txt
Keywords: hive,ionomy,library,api,rpc
Platform: UNKNOWN
Classifier: License :: OSI Approved :: MIT License
Classifier: Operating System :: OS Independent
Classifier: Programming Language :: Python
Classifier: Programming Language :: Python :: 3.6
Classifier: Programming Language :: Python :: 3.7
Classifier: Intended Audience :: Developers
Requires-Python: >=3.6
Requires-Dist: requests
Requires-Dist: arrow
Requires-Dist: furl
Requires-Dist: python-decouple
Requires-Dist: pandas
Requires-Dist: pandas-ta
